pinecone/__init__.py
pinecone/__version__
pinecone/config/__init__.py
pinecone/config/config.py
pinecone/config/openapi.py
pinecone/config/pinecone_config.py
pinecone/control/__init__.py
pinecone/control/index_host_store.py
pinecone/control/langchain_import_warnings.py
pinecone/control/pinecone.py
pinecone/control/repr_overrides.py
pinecone/core/__init__.py
pinecone/core/grpc/protos/vector_service_pb2.py
pinecone/core/grpc/protos/vector_service_pb2.pyi
pinecone/core/grpc/protos/vector_service_pb2_grpc.py
pinecone/core/openapi/control/__init__.py
pinecone/core/openapi/control/api/__init__.py
pinecone/core/openapi/control/api/inference_api.py
pinecone/core/openapi/control/api/manage_indexes_api.py
pinecone/core/openapi/control/apis/__init__.py
pinecone/core/openapi/control/model/__init__.py
pinecone/core/openapi/control/model/collection_list.py
pinecone/core/openapi/control/model/collection_model.py
pinecone/core/openapi/control/model/configure_index_request.py
pinecone/core/openapi/control/model/configure_index_request_spec.py
pinecone/core/openapi/control/model/configure_index_request_spec_pod.py
pinecone/core/openapi/control/model/create_collection_request.py
pinecone/core/openapi/control/model/create_index_request.py
pinecone/core/openapi/control/model/deletion_protection.py
pinecone/core/openapi/control/model/embed_request.py
pinecone/core/openapi/control/model/embed_request_inputs.py
pinecone/core/openapi/control/model/embed_request_parameters.py
pinecone/core/openapi/control/model/embedding.py
pinecone/core/openapi/control/model/embeddings_list.py
pinecone/core/openapi/control/model/embeddings_list_usage.py
pinecone/core/openapi/control/model/error_response.py
pinecone/core/openapi/control/model/error_response_error.py
pinecone/core/openapi/control/model/index_list.py
pinecone/core/openapi/control/model/index_model.py
pinecone/core/openapi/control/model/index_model_spec.py
pinecone/core/openapi/control/model/index_model_status.py
pinecone-5.3.0.dist-info/LICENSE.txt
pinecone-5.3.0.dist-info/METADATA
pinecone-5.3.0.dist-info/WHEEL
pinecone-5.3.0.dist-info/RECORD
